s7smaths/__init__.py
s7smaths/advanced_maths.py
s7smaths/basic_maths.py
s7smaths-1.0.1.dist-info/METADATA
s7smaths-1.0.1.dist-info/WHEEL
s7smaths-1.0.1.dist-info/top_level.txt
s7smaths-1.0.1.dist-info/RECORD
